FuckTikTok/__init__.py
FuckTikTok/api.py
fucktiktok-0.1.0.dist-info/licenses/LICENSE
fucktiktok-0.1.0.dist-info/METADATA
fucktiktok-0.1.0.dist-info/WHEEL
fucktiktok-0.1.0.dist-info/top_level.txt
fucktiktok-0.1.0.dist-info/RECORD
