Metadata-Version: 2.4
Name: FuckTikTok
Version: 0.1.0
Summary: A custom API request handler similar to requests.
Author-email: Your Name <your@email.com>
License: MIT License
Project-URL: Homepage, https://github.com/yourusername/fucktiktok
Classifier: Programming Language :: Python :: 3
Classifier: License :: OSI Approved :: MIT License
Classifier: Operating System :: OS Independent
Requires-Python: >=3.6
License-File: LICENSE
Requires-Dist: requests>=2.25.0
Dynamic: license-file
